README.md
setup.cfg
setup.py
simple_spotify/__init__.py
simple_spotify/api.py
simple_spotify/authcode_fetcher.py
simple_spotify/authorization.py
simple_spotify/consts.py
simple_spotify/decorators.py
simple_spotify/errors.py
simple_spotify/models.py
simple_spotify/util.py
simple_spotify.egg-info/PKG-INFO
simple_spotify.egg-info/SOURCES.txt
simple_spotify.egg-info/dependency_links.txt
simple_spotify.egg-info/entry_points.txt
simple_spotify.egg-info/not-zip-safe
simple_spotify.egg-info/top_level.txt