Metadata-Version: 1.1
Name: simple-spotify
Version: 0.1.3
Summary: Pure Python Spotify Web API wrapper library
Home-page: https://github.com/NaoY-2501/simple_spotify
Author: Naotaka Yokoyama
Author-email: solaris2501.fe2@gmail.com
License: MIT
Platform: UNKNOWN
Classifier: Programming Language :: Python
Classifier: Programming Language :: Python :: 3.5
Classifier: Programming Language :: Python :: 3.6
Classifier: Programming Language :: Python :: 3.7
